strayl_logging/__init__.py
strayl_logging/client.py
strayl_logging-0.2.0.dist-info/METADATA
strayl_logging-0.2.0.dist-info/WHEEL
strayl_logging-0.2.0.dist-info/licenses/LICENSE
strayl_logging-0.2.0.dist-info/RECORD
