Metadata-Version: 2.4
Name: strayl-logging
Version: 0.2.0
Summary: Python SDK for sending logs to Strayl Cortyx
Project-URL: Homepage, https://strayl.dev
Project-URL: Source, https://github.com/AlemzhanJ/strayl-sdk-py
Project-URL: Documentation, https://github.com/AlemzhanJ/strayl-sdk-py#readme
Project-URL: Repository, https://github.com/AlemzhanJ/strayl-sdk-py
Author-email: Strayl <support@strayl.dev>
License: MIT
License-File: LICENSE
Keywords: logging,logs,monitoring,sdk,strayl
Classifier: Development Status :: 4 - Beta
Classifier: Intended Audience :: Developers
Classifier: License :: OSI Approved :: MIT License
Classifier: Programming Language :: Python :: 3
Classifier: Programming Language :: Python :: 3.8
Classifier: Programming Language :: Python :: 3.9
Classifier: Programming Language :: Python :: 3.10
Classifier: Programming Language :: Python :: 3.11
Classifier: Programming Language :: Python :: 3.12
Requires-Python: >=3.8
Requires-Dist: requests>=2.28.0
